mvo_core/__init__.py
mvo_core/mvo.py
mvo_core-0.1.3.dist-info/licenses/AUTHORS.txt
mvo_core-0.1.3.dist-info/licenses/LICENSE
mvo_core-0.1.3.dist-info/METADATA
mvo_core-0.1.3.dist-info/WHEEL
mvo_core-0.1.3.dist-info/top_level.txt
mvo_core-0.1.3.dist-info/RECORD
